MANIFEST.in
README.md
setup.py
rlpp/__init__.py
rlpp/constants.py
rlpp/mainUI.py
rlpp/rlpp_designer.py
rlpp.egg-info/PKG-INFO
rlpp.egg-info/SOURCES.txt
rlpp.egg-info/dependency_links.txt
rlpp.egg-info/entry_points.txt
rlpp.egg-info/requires.txt
rlpp.egg-info/top_level.txt
rlpp/processor/__init__.py
rlpp/processor/processor.py
rlpp/processor/template.txt
rlpp/resources/__init__.py
rlpp/resources/backgrounds/bg_map.png
rlpp/resources/icons/move.png
rlpp/resources/icons/rotate.png
rlpp/resources/icons/select.png
rlpp/resources/icons/stamp.png
rlpp/resources/icons/trash.png
rlpp/resources/originals/utils.py
rlpp/resources/originals/__pycache__/utils.cpython-39.pyc
rlpp/resources/originals/agents/0.png
rlpp/resources/originals/agents/128_bar.png
rlpp/resources/originals/agents/64_4.png
rlpp/resources/originals/agents/agent_0.png
rlpp/resources/originals/agents/bp1.png
rlpp/resources/originals/agents/bp2.png
rlpp/resources/originals/agents/car_1.png
rlpp/resources/originals/agents/car_2.png
rlpp/resources/originals/agents/head.png
rlpp/resources/originals/agents/o.png
rlpp/resources/originals/agents/paddle_0.png
rlpp/resources/originals/agents/prey.png
rlpp/resources/originals/agents/ship.png
rlpp/resources/originals/agents/ship0.png
rlpp/resources/originals/agents/ship2.png
rlpp/resources/originals/agents/ship_typeII.png
rlpp/resources/originals/agents/ship_typeII_2.png
rlpp/resources/originals/agents/ship_typeII_3.png
rlpp/resources/originals/agents/square.png
rlpp/resources/originals/agents/turtle.png
rlpp/resources/originals/enemies/10_cruiserC_60x54.png
rlpp/resources/originals/enemies/3.png
rlpp/resources/originals/enemies/5_cruiserC_60x54.png
rlpp/resources/originals/enemies/64_tank_0.png
rlpp/resources/originals/enemies/7_cruiserC.png
rlpp/resources/originals/enemies/8_cruiserC.png
rlpp/resources/originals/enemies/9_cruiserC_60x54.png
rlpp/resources/originals/enemies/enemy.png
rlpp/resources/originals/enemies/enemy_0.png
rlpp/resources/originals/enemies/paddle_1.png
rlpp/resources/originals/enemies/predator.png
rlpp/resources/originals/enemies/ship_0.png
rlpp/resources/originals/food/11.png
