Metadata-Version: 2.1
Name: rlpp
Version: 0.5.0
Summary: A GUI tool for building Pygame applications and Reinforcement Learning
Home-page: https://github.com/UGarCil/The_RL_Playground_with_python
Author: Uriel Garcilazo Cruz
Author-email: garcilazo.uriel@gmail.com
Classifier: Programming Language :: Python :: 3
Classifier: License :: OSI Approved :: MIT License
Classifier: Operating System :: OS Independent
Requires-Python: >=3.9
Requires-Dist: pygame
Requires-Dist: pyqt5
Requires-Dist: pyqt5-tools
Requires-Dist: opencv-python
Requires-Dist: opencv-contrib-python
